semantic_scholar_search.py
semantic_scholar_server.py
semanticscholar_mcp_server-0.1.0.dist-info/METADATA
semanticscholar_mcp_server-0.1.0.dist-info/WHEEL
semanticscholar_mcp_server-0.1.0.dist-info/entry_points.txt
semanticscholar_mcp_server-0.1.0.dist-info/top_level.txt
semanticscholar_mcp_server-0.1.0.dist-info/RECORD
