Metadata-Version: 2.4
Name: semanticscholar-mcp-server
Version: 0.1.0
Summary: A Model Context Protocol (MCP) server for Semantic Scholar API
Author-email: Jack Kuo <your-email@example.com>
License-Expression: MIT
Project-URL: Homepage, https://github.com/JackKuo666/semanticscholar-MCP-Server
Project-URL: Repository, https://github.com/JackKuo666/semanticscholar-MCP-Server
Classifier: Development Status :: 4 - Beta
Classifier: Intended Audience :: Developers
Classifier: Topic :: Software Development :: Libraries :: Python Modules
Classifier: Programming Language :: Python :: 3
Classifier: Programming Language :: Python :: 3.10
Classifier: Programming Language :: Python :: 3.11
Classifier: Programming Language :: Python :: 3.12
Requires-Python: >=3.10
Requires-Dist: semanticscholar>=0.7.0
Requires-Dist: mcp>=1.0.0
Requires-Dist: requests>=2.25.0
Requires-Dist: beautifulsoup4>=4.9.0
